ampel/abstract/AbsAlertFilter.py
ampel/abstract/AbsAlertLoader.py
ampel/abstract/AbsAlertRegister.py
ampel/abstract/AbsAlertSupplier.py
ampel/alert/AlertConsumer.py
ampel/alert/AlertConsumerError.py
ampel/alert/AlertConsumerMetrics.py
ampel/alert/AlertFileList.py
ampel/alert/BaseAlertSupplier.py
ampel/alert/FilterBlock.py
ampel/alert/FilterBlocksHandler.py
ampel/alert/FilteringAlertSupplier.py
ampel/alert/filter/BasicMultiFilter.py
ampel/alert/load/DirAlertLoader.py
ampel/alert/load/DirFileNamesLoader.py
ampel/alert/load/DirTaggedAlertLoader.py
ampel/alert/load/FileAlertLoader.py
ampel/alert/load/TarAlertLoader.py
ampel/alert/load/TarballWalker.py
ampel/alert/reject/BaseAlertRegister.py
ampel/alert/reject/DBRejectedLogsHandler.py
ampel/alert/reject/FullActiveAlertRegister.py
ampel/alert/reject/FullAlertRegister.py
ampel/alert/reject/GeneralActiveAlertRegister.py
ampel/alert/reject/GeneralAlertRegister.py
ampel/alert/reject/MinimalActiveAlertRegister.py
ampel/alert/reject/MinimalAlertRegister.py
ampel/dev/AutoCompleteBenchmark.py
ampel/dev/UnitTestAlertSupplier.py
ampel/model/AlertConsumerModel.py
ampel/py.typed
ampel/template/AbsEasyChannelTemplate.py
ampel/template/EasyAlertConsumerTemplate.py
conf/ampel-alerts/ampel.yml
ampel_alerts-0.10.1.dist-info/LICENSE
ampel_alerts-0.10.1.dist-info/METADATA
ampel_alerts-0.10.1.dist-info/WHEEL
ampel_alerts-0.10.1.dist-info/RECORD
