Metadata-Version: 2.1
Name: ampel-alerts
Version: 0.10.1
Summary: Alert support for the Ampel system
Home-page: https://ampelproject.github.io
License: BSD-3-Clause
Author: Valery Brinnel
Maintainer: Jakob van Santen
Maintainer-email: jakob.van.santen@desy.de
Requires-Python: >=3.10,<4.0
Classifier: Development Status :: 4 - Beta
Classifier: Intended Audience :: Science/Research
Classifier: License :: OSI Approved :: BSD License
Classifier: Programming Language :: Python :: 3
Classifier: Programming Language :: Python :: 3.10
Classifier: Programming Language :: Python :: 3.11
Classifier: Programming Language :: Python :: 3.12
Classifier: Topic :: Scientific/Engineering :: Astronomy
Classifier: Topic :: Scientific/Engineering :: Information Analysis
Classifier: Typing :: Typed
Requires-Dist: ampel-core (>=0.10.0a0,<0.11)
Project-URL: Repository, https://github.com/AmpelProject/Ampel-alerts
